README.rst
setup.py
lcase/__init__.py
lcase.egg-info/PKG-INFO
lcase.egg-info/SOURCES.txt
lcase.egg-info/dependency_links.txt
lcase.egg-info/requires.txt
lcase.egg-info/top_level.txt
lcase/causality/__init__.py
lcase/causality/gin.py
lcase/causality/triad.py
lcase/datasets/__init__.py
lcase/datasets/simulation.py
lcase/graphs/__init__.py
lcase/graphs/_graphutils.py
lcase/graphs/causalgraph.py
lcase/independence/__init__.py
lcase/independence/_base_independence.py
lcase/independence/fisherZ.py
lcase/independence/hsic.py
lcase/independence/kci.py
lcase/independence/kmi.py
lcase/utils/__init__.py
lcase/utils/cumulant.py
lcase/utils/overlap_cluster.py
lcase/utils/kernel/GaussianKernel.py
lcase/utils/kernel/Kernel.py
lcase/utils/kernel/__init__.py
tests/__init__.py
tests/test_gin.py
tests/test_triad.py