Metadata-Version: 2.1
Name: lcase
Version: 0.0.5
Summary: Latent CAusal Structure Estimator Python Package
Home-page: https://github.com/zhi-yi-huang/lcase
Author: Zhiyi Huang
License: UNKNOWN
Platform: UNKNOWN
Classifier: Programming Language :: Python :: 3
Classifier: Operating System :: OS Independent
Requires-Python: >=3.6
